Metadata-Version: 2.1
Name: probabi-distributions
Version: 1.0
Summary: Gaussian and Binomial distributions
Home-page: UNKNOWN
Author: Darshit Sharma
License: UNKNOWN
Platform: UNKNOWN
